test_cmd.py
test_cmd-2.0.6.dist-info/LICENSE.txt
test_cmd-2.0.6.dist-info/METADATA
test_cmd-2.0.6.dist-info/WHEEL
test_cmd-2.0.6.dist-info/entry_points.txt
test_cmd-2.0.6.dist-info/top_level.txt
test_cmd-2.0.6.dist-info/RECORD
