Metadata-Version: 2.1
Name: test_cmd
Version: 2.0.6
Summary: Tool for black-box testing command-line programs using STDIN, STDOUT and STDERR, with multiple CPUs
Home-page: https://github.com/arjun-menon/test_cmd
Download-URL: https://github.com/arjun-menon/test_cmd/archive/v2.0.6.tar.gz
Author: Arjun G. Menon
Author-email: contact@arjungmenon.com
License: Apache-2.0
Keywords: command line terminal functional black box testing arguments stdin stdout stderr
Classifier: Topic :: Software Development :: Quality Assurance
Classifier: Topic :: Software Development :: Testing
Classifier: License :: OSI Approved :: Apache Software License
Classifier: Environment :: Console
License-File: LICENSE.txt
